s3200/__init__.py
s3200/const.py
s3200/core.py
s3200/net.py
s3200/obj.py
s3200/test/__init__.py
s3200/test/dummy.py
s3200/test/test_connection.py
s3200/test/test_s3200.py
s3200-0.0.2.dist-info/METADATA
s3200-0.0.2.dist-info/WHEEL
s3200-0.0.2.dist-info/top_level.txt
s3200-0.0.2.dist-info/RECORD
