Metadata-Version: 2.1
Name: s3200
Version: 0.0.2
Summary: A Python package for controlling the Fröling heating system (S3200) over the maintenance interface
Home-page: https://github.com/cbasix/s3200
Author: cbasix
Author-email: cbasix@users.noreply.github.com
License: UNKNOWN
Platform: UNKNOWN
Classifier: Programming Language :: Python :: 3
Classifier: License :: OSI Approved :: Apache Software License
Classifier: Development Status :: 4 - Beta
Classifier: Operating System :: OS Independent
Requires-Python: >=3.6
Requires-Dist: pyserial
